sun_angles/SHA_deg_from_DOY_lat.py
sun_angles/SZA_deg_from_lat_dec_hour.py
sun_angles/__init__.py
sun_angles/calculate_SZA_from_DOY_and_hour.py
sun_angles/calculate_SZA_from_datetime.py
sun_angles/calculate_daylight.py
sun_angles/calculate_solar_azimuth.py
sun_angles/calculate_sunrise.py
sun_angles/day_angle_rad_from_DOY.py
sun_angles/daylight_from_SHA.py
sun_angles/solar_dec_deg_from_day_angle_rad.py
sun_angles/sun_angles.py
sun_angles/sunrise_from_SHA.py
sun_angles/version.py
sun_angles-1.7.0.dist-info/licenses/LICENSE
sun_angles-1.7.0.dist-info/METADATA
sun_angles-1.7.0.dist-info/WHEEL
sun_angles-1.7.0.dist-info/top_level.txt
sun_angles-1.7.0.dist-info/RECORD
